Invoke/Invoke.py
Invoke/__init__.py
AWS_Invoke-0.0.2.dist-info/LICENSE
AWS_Invoke-0.0.2.dist-info/METADATA
AWS_Invoke-0.0.2.dist-info/WHEEL
AWS_Invoke-0.0.2.dist-info/top_level.txt
AWS_Invoke-0.0.2.dist-info/RECORD
