Metadata-Version: 2.1
Name: AWS-Invoke
Version: 0.0.2
Summary: Python library for Invoking a targeted AWS Lambda function based on the provied event
Home-page: https://github.com/pentairiot/Invoke
Author: PentairIoT
Author-email: pentairiot@gmail.com
License: UNKNOWN
Platform: UNKNOWN
Classifier: Programming Language :: Python :: 3
Classifier: License :: OSI Approved :: MIT License
Classifier: Operating System :: OS Independent
Requires-Dist: boto3
